wscraping_helper/__init__.py
wscraping_helper/helper.py
wscraping_helper-1.0.1.dist-info/METADATA
wscraping_helper-1.0.1.dist-info/WHEEL
wscraping_helper-1.0.1.dist-info/top_level.txt
wscraping_helper-1.0.1.dist-info/RECORD
